azure/identity/__init__.py
azure/identity/_auth_record.py
azure/identity/_bearer_token_provider.py
azure/identity/_constants.py
azure/identity/_enums.py
azure/identity/_exceptions.py
azure/identity/_persistent_cache.py
azure/identity/_version.py
azure/identity/py.typed
azure/identity/_credentials/__init__.py
azure/identity/_credentials/app_service.py
azure/identity/_credentials/application.py
azure/identity/_credentials/authorization_code.py
azure/identity/_credentials/azd_cli.py
azure/identity/_credentials/azure_arc.py
azure/identity/_credentials/azure_cli.py
azure/identity/_credentials/azure_ml.py
azure/identity/_credentials/azure_pipelines.py
azure/identity/_credentials/azure_powershell.py
azure/identity/_credentials/browser.py
azure/identity/_credentials/certificate.py
azure/identity/_credentials/chained.py
azure/identity/_credentials/client_assertion.py
azure/identity/_credentials/client_secret.py
azure/identity/_credentials/cloud_shell.py
azure/identity/_credentials/default.py
azure/identity/_credentials/device_code.py
azure/identity/_credentials/environment.py
azure/identity/_credentials/imds.py
azure/identity/_credentials/managed_identity.py
azure/identity/_credentials/on_behalf_of.py
azure/identity/_credentials/service_fabric.py
azure/identity/_credentials/shared_cache.py
azure/identity/_credentials/silent.py
azure/identity/_credentials/user_password.py
azure/identity/_credentials/vscode.py
azure/identity/_credentials/workload_identity.py
azure/identity/_internal/__init__.py
azure/identity/_internal/aad_client.py
azure/identity/_internal/aad_client_base.py
azure/identity/_internal/aadclient_certificate.py
azure/identity/_internal/auth_code_redirect_handler.py
azure/identity/_internal/client_credential_base.py
azure/identity/_internal/decorators.py
azure/identity/_internal/get_token_mixin.py
azure/identity/_internal/interactive.py
azure/identity/_internal/linux_vscode_adapter.py
azure/identity/_internal/macos_vscode_adapter.py
azure_identity-1.19.0.dist-info/LICENSE
azure_identity-1.19.0.dist-info/METADATA
azure_identity-1.19.0.dist-info/WHEEL
azure_identity-1.19.0.dist-info/top_level.txt
azure_identity-1.19.0.dist-info/RECORD
